ofnodes/__init__.py
ofnodes/components/__init__.py
ofnodes/components/nodes/__init__ copy.py
ofnodes/components/nodes/__init__.py
ofnodes/components/nodes/descriptors.py
ofnodes/components/nodes/mixins.py
ofnodes/components/structures/__init__.py
ofnodes/components/structures/descriptors.py
ofnodes/components/structures/mixins.py
ofnodes/logging_config.py
ofnodes/nodes/__init__.py
ofnodes/nodes/singlynode.py
ofnodes/py.typed
ofnodes/sorting/__init__.py
ofnodes/sorting/mixins.py
ofnodes/structures/__init__.py
ofnodes/structures/randomaccessarray.py
ofnodes/structures/singlylinkedlist.py
ofnodes/structures/stack.py
ofnodes-2.2.1.dist-info/LICENSE
ofnodes-2.2.1.dist-info/METADATA
ofnodes-2.2.1.dist-info/WHEEL
ofnodes-2.2.1.dist-info/RECORD
