Metadata-Version: 2.1
Name: ofnodes
Version: 2.2.1
Summary: A library of Data Structures and Algorithms written in Python
Author: Robert Portelli
Author-email: github@robertportelli.com
Requires-Python: >=3.11,<4.0
Classifier: Programming Language :: Python :: 3
Classifier: Programming Language :: Python :: 3.11
Classifier: Programming Language :: Python :: 3.12
